CMakeLists.txt
LICENSE
MANIFEST.in
README.md
requirements.txt
setup.py
data/README.md
data/SKYMAP_SKY2000_V5R4.gz
data/SKYMAP_SKY2000_V5R4_Sources_and_Data_Representation.pdf
data/SKYMAP_SKY2000_V5R4_Specifications.pdf
data/cat
data/skymap-brightest-8876
data/skymap-brightest-8876.csv
data/skymap-old-matlab-reader.m
libstarid/CMakeLists.txt
libstarid/api.cpp
libstarid/api.h
libstarid/sky.cpp
libstarid/sky.h
libstarid/skymap.cpp
libstarid/skymap.h
libstarid/starpairs.cpp
libstarid/starpairs.h
libstarid/startriangle.cpp
libstarid/startriangle.h
libstarid/startriangleidentifier.cpp
libstarid/startriangleidentifier.h
libstarid/startriangleside.cpp
libstarid/startriangleside.h
libstarid/util.cpp
libstarid/util.h
starid/__init__.py
starid/__main__.py
starid/demo.py
starid/version.py
starid.egg-info/PKG-INFO
starid.egg-info/SOURCES.txt
starid.egg-info/dependency_links.txt
starid.egg-info/entry_points.txt
starid.egg-info/requires.txt
starid.egg-info/top_level.txt
starid/__pycache__/__init__.cpython-38.pyc
starid/__pycache__/__main__.cpython-38.pyc
starid/__pycache__/demo.cpython-38.pyc
starid/__pycache__/version.cpython-38.pyc
starid/tests/test_demo.py
starid/tests/__pycache__/test_demo.cpython-38-pytest-7.1.1.pyc