Metadata-Version: 2.1
Name: starid
Version: 1.5.1
Summary: star identification
Home-page: https://gitlab.com/noahhsmith/starid
Author: noah smith
Author-email: noahhsmith@gmail.com
License: UNKNOWN
Platform: UNKNOWN
Classifier: Programming Language :: Python :: 3
Classifier: License :: OSI Approved :: MIT License
Classifier: Operating System :: OS Independent
